Project_Xpert/__init__.py
Project_Xpert/__main__.py
Project_Xpert/autorun.py
Project_Xpert/capture.py
Project_Xpert/cleanup.py
Project_Xpert/main.py
Project_Xpert/ocr_export.py
xpert_ad_targeting-1.0.0.dist-info/METADATA
xpert_ad_targeting-1.0.0.dist-info/WHEEL
xpert_ad_targeting-1.0.0.dist-info/entry_points.txt
xpert_ad_targeting-1.0.0.dist-info/top_level.txt
xpert_ad_targeting-1.0.0.dist-info/RECORD
