Metadata-Version: 2.4
Name: xpert-ad-targeting
Version: 1.0.0
Summary: Automated POS monitoring and OCR processing application
Author: XPERT Team
Author-email: XPERT Team <support@xpert.chat>
License-Expression: MIT
Project-URL: Bug Reports, https://github.com/xpert-team/xpert-ad-targeting/issues
Project-URL: Source, https://github.com/xpert-team/xpert-ad-targeting
Keywords: pos,monitoring,ocr,automation,gui
Classifier: Development Status :: 4 - Beta
Classifier: Intended Audience :: End Users/Desktop
Classifier: Operating System :: OS Independent
Classifier: Programming Language :: Python :: 3
Classifier: Programming Language :: Python :: 3.8
Classifier: Programming Language :: Python :: 3.9
Classifier: Programming Language :: Python :: 3.10
Classifier: Programming Language :: Python :: 3.11
Requires-Python: >=3.8
Requires-Dist: customtkinter>=5.2.0
Requires-Dist: Pillow>=9.0.0
Requires-Dist: pytesseract>=0.3.10
Requires-Dist: opencv-python>=4.5.0
Requires-Dist: pymongo>=4.0.0
Requires-Dist: boto3>=1.26.0
Requires-Dist: python-dotenv>=0.19.0
Requires-Dist: keyboard>=0.13.5
Requires-Dist: pyautogui>=0.9.54
Requires-Dist: pygetwindow>=0.0.9
Requires-Dist: requests>=2.28.0
Requires-Dist: numpy>=1.21.0
Requires-Dist: scikit-image>=0.19.0
Requires-Dist: scipy>=1.7.0
Dynamic: author
Dynamic: requires-python
